cybrushwifi/__init__.py
cybrushwifi/alerts.py
cybrushwifi/export.py
cybrushwifi/gui.py
cybrushwifi/history.py
cybrushwifi/scanner.py
cybrushwifi/utils.py
cybrushwifi-1.0.0.dist-info/METADATA
cybrushwifi-1.0.0.dist-info/WHEEL
cybrushwifi-1.0.0.dist-info/entry_points.txt
cybrushwifi-1.0.0.dist-info/top_level.txt
cybrushwifi-1.0.0.dist-info/RECORD
