Metadata-Version: 2.4
Name: cybrushwifi
Version: 1.0.0
Summary: Professional Wi-Fi security scanning and monitoring tool
Author: Cybrush Security
Author-email: contact@cybrushsecurity.com
Classifier: Development Status :: 4 - Beta
Classifier: Intended Audience :: Developers
Classifier: Intended Audience :: Information Technology
Classifier: Topic :: Security
Classifier: Topic :: System :: Networking
Classifier: Programming Language :: Python :: 3
Classifier: Operating System :: OS Independent
Requires-Python: >=3.8
Requires-Dist: pywebview
Requires-Dist: requests
Requires-Dist: reportlab
Dynamic: author
Dynamic: author-email
Dynamic: classifier
Dynamic: description
Dynamic: description-content-type
Dynamic: requires-dist
Dynamic: requires-python
Dynamic: summary
